Workbook
Name age_when_money_runs_out: Support!$B$9
Name ann_income_increase: Planner!$B$12
Name ann_inflation: Planner!$B$11
Name cur_age: Planner!$B$5
Name cur_expenses: Planner!$B$7
Name cur_income: Planner!$B$6
Name cur_ret_saving: Planner!$B$8
Name des_rit_age: Planner!$B$2
Name dynamic_labels: OFFSET(Detail!$A$2,0,0,[0]!years_before_money_runs_out,1)
Name dynamic_labels: OFFSET(Calculations!$B$2,0,0,years_before_money_runs_out,1)
Name dynamic_series: OFFSET(Detail!$I$2,0,0,[0]!years_before_money_runs_out,1)
Name dynamic_series: OFFSET(Calculations!$J$2,0,0,years_before_money_runs_out,1)
Name post_inv_return: Support!$B$6
Name pre_inv_return: Support!$B$5
Name tax_rate: Planner!$B$13
Name years_before_money_runs_out: Support!$B$8

Sheet Planner
A1: Desired Retirement Age | D1: =IF(years_before_money_runs_out>=100,"You willl NEVER run out", "You will run out of money at " &age_when_money_runs_out& " years old") -> You will run out of money at 87 years old
B2: 61
A4: Current Information
A5: Current Age | B5: 29
A6: Current Annual Income | B6: 75000
A7: Current Annual Expenses | B7: 60000
A8: Current Retirement Savings | B8: 21000
A10: Economic Assumptions
A11: Annual Inflation | B11: 0.03
A12: Annual Income Increase | B12: 0.04
A13: Tax Rate | B13: 0.1
A15: Risk Tolerance (Pre-Retirement)
A16: Aggressive (Est. 8% Annual Return)
A18: Risk Tolerance (Post-Retirement)
A19: Conservative (Est. 4% Annual Return)

Sheet Detail
A1: Age | B1: Working Income | C1: Income Tax | D1: Yearly Expenditures | E1: Yearly Savings | F1: Beginning Savings Balance | G1: Earned Interest | H1: Retirement Savings Withdrawal | I1: End Savings Balance | J1: Overall Net Gain/Loss
A2: =IF(Calculations!$B2<age_when_money_runs_out,Calculations!B2,"") -> 29 | B2: =IF(Calculations!$B2<age_when_money_runs_out,Calculations!C2,"") -> 75000 | C2: =IF(Calculations!$B2<age_when_money_runs_out,Calculations!D2,"") -> 7500 | D2: =IF(Calculations!$B2<age_when_money_runs_out,Calculations!E2,"") -> 60000 | E2: =IF(Calculations!$B2<age_when_money_runs_out,Calculations!F2,"") -> 7500 | F2: =IF(Calculations!$B2<age_when_money_runs_out,Calculations!G2,"") -> 21000 | G2: =IF(Calculations!$B2<age_when_money_runs_out,Calculations!H2,"") -> 1680 | H2: =IF(Calculations!$B2<age_when_money_runs_out,Calculations!I2,"") -> 0 | ... J2: =IF(Calculations!$B2<age_when_money_runs_out,Calculations!K2,"") -> 9180
A3: =IF(Calculations!$B3<age_when_money_runs_out,Calculations!B3,"") -> 30 | B3: =IF(Calculations!$B3<age_when_money_runs_out,Calculations!C3,"") -> 78000 | C3: =IF(Calculations!$B3<age_when_money_runs_out,Calculations!D3,"") -> 7800 | D3: =IF(Calculations!$B3<age_when_money_runs_out,Calculations!E3,"") -> 61800 | E3: =IF(Calculations!$B3<age_when_money_runs_out,Calculations!F3,"") -> 8400 | F3: =IF(Calculations!$B3<age_when_money_runs_out,Calculations!G3,"") -> 30180 | G3: =IF(Calculations!$B3<age_when_money_runs_out,Calculations!H3,"") -> 2414.4 | H3: =IF(Calculations!$B3<age_when_money_runs_out,Calculations!I3,"") -> 0 | ... J3: =IF(Calculations!$B3<age_when_money_runs_out,Calculations!K3,"") -> 10814.4
A4: =IF(Calculations!$B4<age_when_money_runs_out,Calculations!B4,"") -> 31 | B4: =IF(Calculations!$B4<age_when_money_runs_out,Calculations!C4,"") -> 81120 | C4: =IF(Calculations!$B4<age_when_money_runs_out,Calculations!D4,"") -> 8112 | D4: =IF(Calculations!$B4<age_when_money_runs_out,Calculations!E4,"") -> 63654 | E4: =IF(Calculations!$B4<age_when_money_runs_out,Calculations!F4,"") -> 9354 | F4: =IF(Calculations!$B4<age_when_money_runs_out,Calculations!G4,"") -> 40994.4 | G4: =IF(Calculations!$B4<age_when_money_runs_out,Calculations!H4,"") -> 3279.552 | H4: =IF(Calculations!$B4<age_when_money_runs_out,Calculations!I4,"") -> 0 | ... J4: =IF(Calculations!$B4<age_when_money_runs_out,Calculations!K4,"") -> 12633.552
A5: =IF(Calculations!$B5<age_when_money_runs_out,Calculations!B5,"") -> 32 | B5: =IF(Calculations!$B5<age_when_money_runs_out,Calculations!C5,"") -> 84364.8 | C5: =IF(Calculations!$B5<age_when_money_runs_out,Calculations!D5,"") -> 8436.48 | D5: =IF(Calculations!$B5<age_when_money_runs_out,Calculations!E5,"") -> 65563.62 | E5: =IF(Calculations!$B5<age_when_money_runs_out,Calculations!F5,"") -> 10364.7 | F5: =IF(Calculations!$B5<age_when_money_runs_out,Calculations!G5,"") -> 53627.952 | G5: =IF(Calculations!$B5<age_when_money_runs_out,Calculations!H5,"") -> 4290.2362 | H5: =IF(Calculations!$B5<age_when_money_runs_out,Calculations!I5,"") -> 0 | ... J5: =IF(Calculations!$B5<age_when_money_runs_out,Calculations!K5,"") -> 14654.936
A6: =IF(Calculations!$B6<age_when_money_runs_out,Calculations!B6,"") -> 33 | B6: =IF(Calculations!$B6<age_when_money_runs_out,Calculations!C6,"") -> 87739.392 | C6: =IF(Calculations!$B6<age_when_money_runs_out,Calculations!D6,"") -> 8773.9392 | D6: =IF(Calculations!$B6<age_when_money_runs_out,Calculations!E6,"") -> 67530.529 | E6: =IF(Calculations!$B6<age_when_money_runs_out,Calculations!F6,"") -> 11434.924 | F6: =IF(Calculations!$B6<age_when_money_runs_out,Calculations!G6,"") -> 68282.888 | G6: =IF(Calculations!$B6<age_when_money_runs_out,Calculations!H6,"") -> 5462.6311 | H6: =IF(Calculations!$B6<age_when_money_runs_out,Calculations!I6,"") -> 0 | ... J6: =IF(Calculations!$B6<age_when_money_runs_out,Calculations!K6,"") -> 16897.555
A7: =IF(Calculations!$B7<age_when_money_runs_out,Calculations!B7,"") -> 34 | B7: =IF(Calculations!$B7<age_when_money_runs_out,Calculations!C7,"") -> 91248.968 | C7: =IF(Calculations!$B7<age_when_money_runs_out,Calculations!D7,"") -> 9124.8968 | D7: =IF(Calculations!$B7<age_when_money_runs_out,Calculations!E7,"") -> 69556.444 | E7: =IF(Calculations!$B7<age_when_money_runs_out,Calculations!F7,"") -> 12567.626 | F7: =IF(Calculations!$B7<age_when_money_runs_out,Calculations!G7,"") -> 85180.443 | G7: =IF(Calculations!$B7<age_when_money_runs_out,Calculations!H7,"") -> 6814.4355 | H7: =IF(Calculations!$B7<age_when_money_runs_out,Calculations!I7,"") -> 0 | ... J7: =IF(Calculations!$B7<age_when_money_runs_out,Calculations!K7,"") -> 19382.062
A8: =IF(Calculations!$B8<age_when_money_runs_out,Calculations!B8,"") -> 35 | B8: =IF(Calculations!$B8<age_when_money_runs_out,Calculations!C8,"") -> 94898.926 | C8: =IF(Calculations!$B8<age_when_money_runs_out,Calculations!D8,"") -> 9489.8926 | D8: =IF(Calculations!$B8<age_when_money_runs_out,Calculations!E8,"") -> 71643.138 | E8: =IF(Calculations!$B8<age_when_money_runs_out,Calculations!F8,"") -> 13765.896 | F8: =IF(Calculations!$B8<age_when_money_runs_out,Calculations!G8,"") -> 104562.51 | G8: =IF(Calculations!$B8<age_when_money_runs_out,Calculations!H8,"") -> 8365.0004 | H8: =IF(Calculations!$B8<age_when_money_runs_out,Calculations!I8,"") -> 0 | ... J8: =IF(Calculations!$B8<age_when_money_runs_out,Calculations!K8,"") -> 22130.896
A9: =IF(Calculations!$B9<age_when_money_runs_out,Calculations!B9,"") -> 36 | B9: =IF(Calculations!$B9<age_when_money_runs_out,Calculations!C9,"") -> 98694.883 | C9: =IF(Calculations!$B9<age_when_money_runs_out,Calculations!D9,"") -> 9869.4883 | D9: =IF(Calculations!$B9<age_when_money_runs_out,Calculations!E9,"") -> 73792.432 | E9: =IF(Calculations!$B9<age_when_money_runs_out,Calculations!F9,"") -> 15032.963 | F9: =IF(Calculations!$B9<age_when_money_runs_out,Calculations!G9,"") -> 126693.4 | G9: =IF(Calculations!$B9<age_when_money_runs_out,Calculations!H9,"") -> 10135.472 | H9: =IF(Calculations!$B9<age_when_money_runs_out,Calculations!I9,"") -> 0 | ... J9: =IF(Calculations!$B9<age_when_money_runs_out,Calculations!K9,"") -> 25168.435
A10: =IF(Calculations!$B10<age_when_money_runs_out,Calculations!B10,"") -> 37 | B10: =IF(Calculations!$B10<age_when_money_runs_out,Calculations!C10,"") -> 102642.68 | C10: =IF(Calculations!$B10<age_when_money_runs_out,Calculations!D10,"") -> 10264.268 | D10: =IF(Calculations!$B10<age_when_money_runs_out,Calculations!E10,"") -> 76006.205 | E10: =IF(Calculations!$B10<age_when_money_runs_out,Calculations!F10,"") -> 16372.206 | F10: =IF(Calculations!$B10<age_when_money_runs_out,Calculations!G10,"") -> 151861.84 | G10: =IF(Calculations!$B10<age_when_money_runs_out,Calculations!H10,"") -> 12148.947 | H10: =IF(Calculations!$B10<age_when_money_runs_out,Calculations!I10,"") -> 0 | ... J10: =IF(Calculations!$B10<age_when_money_runs_out,Calculations!K10,"") -> 28521.153
A11: =IF(Calculations!$B11<age_when_money_runs_out,Calculations!B11,"") -> 38 | B11: =IF(Calculations!$B11<age_when_money_runs_out,Calculations!C11,"") -> 106748.39 | C11: =IF(Calculations!$B11<age_when_money_runs_out,Calculations!D11,"") -> 10674.839 | D11: =IF(Calculations!$B11<age_when_money_runs_out,Calculations!E11,"") -> 78286.391 | E11: =IF(Calculations!$B11<age_when_money_runs_out,Calculations!F11,"") -> 17787.156 | F11: =IF(Calculations!$B11<age_when_money_runs_out,Calculations!G11,"") -> 180382.99 | G11: =IF(Calculations!$B11<age_when_money_runs_out,Calculations!H11,"") -> 14430.639 | H11: =IF(Calculations!$B11<age_when_money_runs_out,Calculations!I11,"") -> 0 | ... J11: =IF(Calculations!$B11<age_when_money_runs_out,Calculations!K11,"") -> 32217.796
A12: =IF(Calculations!$B12<age_when_money_runs_out,Calculations!B12,"") -> 39 | B12: =IF(Calculations!$B12<age_when_money_runs_out,Calculations!C12,"") -> 111018.32 | C12: =IF(Calculations!$B12<age_when_money_runs_out,Calculations!D12,"") -> 11101.832 | D12: =IF(Calculations!$B12<age_when_money_runs_out,Calculations!E12,"") -> 80634.983 | E12: =IF(Calculations!$B12<age_when_money_runs_out,Calculations!F12,"") -> 19281.506 | F12: =IF(Calculations!$B12<age_when_money_runs_out,Calculations!G12,"") -> 212600.79 | G12: =IF(Calculations!$B12<age_when_money_runs_out,Calculations!H12,"") -> 17008.063 | H12: =IF(Calculations!$B12<age_when_money_runs_out,Calculations!I12,"") -> 0 | ... J12: =IF(Calculations!$B12<age_when_money_runs_out,Calculations!K12,"") -> 36289.569
A13: =IF(Calculations!$B13<age_when_money_runs_out,Calculations!B13,"") -> 40 | B13: =IF(Calculations!$B13<age_when_money_runs_out,Calculations!C13,"") -> 115459.05 | C13: =IF(Calculations!$B13<age_when_money_runs_out,Calculations!D13,"") -> 11545.905 | D13: =IF(Calculations!$B13<age_when_money_runs_out,Calculations!E13,"") -> 83054.032 | E13: =IF(Calculations!$B13<age_when_money_runs_out,Calculations!F13,"") -> 20859.117 | F13: =IF(Calculations!$B13<age_when_money_runs_out,Calculations!G13,"") -> 248890.35 | G13: =IF(Calculations!$B13<age_when_money_runs_out,Calculations!H13,"") -> 19911.228 | H13: =IF(Calculations!$B13<age_when_money_runs_out,Calculations!I13,"") -> 0 | ... J13: =IF(Calculations!$B13<age_when_money_runs_out,Calculations!K13,"") -> 40770.345
... A101: =IF(Calculations!$B101<age_when_money_runs_out,Calculations!B101,"") | B101: =IF(Calculations!$B101<age_when_money_runs_out,Calculations!C101,"") | C101: =IF(Calculations!$B101<age_when_money_runs_out,Calculations!D101,"") | D101: =IF(Calculations!$B101<age_when_money_runs_out,Calculations!E101,"") | E101: =IF(Calculations!$B101<age_when_money_runs_out,Calculations!F101,"") | F101: =IF(Calculations!$B101<age_when_money_runs_out,Calculations!G101,"") | G101: =IF(Calculations!$B101<age_when_money_runs_out,Calculations!H101,"") | H101: =IF(Calculations!$B101<age_when_money_runs_out,Calculations!I101,"") | ... J101: =IF(Calculations!$B101<age_when_money_runs_out,Calculations!K101,"")

Sheet Calculations
A1: Plan Year | B1: Age | C1: Working Income | D1: Income Tax | E1: Yearly Expenditures | F1: Yearly Savings | G1: Beginning Savings Balance | H1: Earned Interest | I1: Retirement Savings Withdrawl | J1: End Savings Balance | K1: Overall Net Gain/Loss
A2: 1 | B2: =cur_age -> 29 | C2: =cur_income -> 75000 | D2: =C2*tax_rate -> 7500 | E2: =cur_expenses -> 60000 | F2: =C2-(D2+E2) -> 7500 | G2: =cur_ret_saving -> 21000 | H2: =G2*pre_inv_return -> 1680 | I2: =IF(des_rit_age>B2,0,E2) -> 0 | J2: =G2+(F2+H2)-I2 -> 30180 | K2: =J2-G2 -> 9180
A3: =1+A2 -> 2 | B3: =1+B2 -> 30 | C3: =IF(des_rit_age>B2,C2+(C2*ann_income_increase),0) -> 78000 | D3: =C3*tax_rate -> 7800 | E3: =E2+(E2*ann_inflation) -> 61800 | F3: =IF(des_rit_age>B2,C3-(D3+E3),0) -> 8400 | G3: =J2 -> 30180 | H3: =IF(des_rit_age>B2,G3*pre_inv_return,G3*post_inv_return) -> 2414.4 | I3: =IF(des_rit_age>B2,0,E3) -> 0 | J3: =G3+(F3+H3)-I3 -> 40994.4 | K3: =J3-G3 -> 10814.4
A4: =1+A3 -> 3 | B4: =1+B3 -> 31 | C4: =IF(des_rit_age>B3,C3+(C3*ann_income_increase),0) -> 81120 | D4: =C4*tax_rate -> 8112 | E4: =E3+(E3*ann_inflation) -> 63654 | F4: =IF(des_rit_age>B3,C4-(D4+E4),0) -> 9354 | G4: =J3 -> 40994.4 | H4: =IF(des_rit_age>B3,G4*pre_inv_return,G4*post_inv_return) -> 3279.552 | I4: =IF(des_rit_age>B3,0,E4) -> 0 | J4: =G4+(F4+H4)-I4 -> 53627.952 | K4: =J4-G4 -> 12633.552
A5: =1+A4 -> 4 | B5: =1+B4 -> 32 | C5: =IF(des_rit_age>B4,C4+(C4*ann_income_increase),0) -> 84364.8 | D5: =C5*tax_rate -> 8436.48 | E5: =E4+(E4*ann_inflation) -> 65563.62 | F5: =IF(des_rit_age>B4,C5-(D5+E5),0) -> 10364.7 | G5: =J4 -> 53627.952 | H5: =IF(des_rit_age>B4,G5*pre_inv_return,G5*post_inv_return) -> 4290.2362 | I5: =IF(des_rit_age>B4,0,E5) -> 0 | J5: =G5+(F5+H5)-I5 -> 68282.888 | K5: =J5-G5 -> 14654.936
A6: =1+A5 -> 5 | B6: =1+B5 -> 33 | C6: =IF(des_rit_age>B5,C5+(C5*ann_income_increase),0) -> 87739.392 | D6: =C6*tax_rate -> 8773.9392 | E6: =E5+(E5*ann_inflation) -> 67530.529 | F6: =IF(des_rit_age>B5,C6-(D6+E6),0) -> 11434.924 | G6: =J5 -> 68282.888 | H6: =IF(des_rit_age>B5,G6*pre_inv_return,G6*post_inv_return) -> 5462.6311 | I6: =IF(des_rit_age>B5,0,E6) -> 0 | J6: =G6+(F6+H6)-I6 -> 85180.443 | K6: =J6-G6 -> 16897.555
A7: =1+A6 -> 6 | B7: =1+B6 -> 34 | C7: =IF(des_rit_age>B6,C6+(C6*ann_income_increase),0) -> 91248.968 | D7: =C7*tax_rate -> 9124.8968 | E7: =E6+(E6*ann_inflation) -> 69556.444 | F7: =IF(des_rit_age>B6,C7-(D7+E7),0) -> 12567.626 | G7: =J6 -> 85180.443 | H7: =IF(des_rit_age>B6,G7*pre_inv_return,G7*post_inv_return) -> 6814.4355 | I7: =IF(des_rit_age>B6,0,E7) -> 0 | J7: =G7+(F7+H7)-I7 -> 104562.51 | K7: =J7-G7 -> 19382.062
A8: =1+A7 -> 7 | B8: =1+B7 -> 35 | C8: =IF(des_rit_age>B7,C7+(C7*ann_income_increase),0) -> 94898.926 | D8: =C8*tax_rate -> 9489.8926 | E8: =E7+(E7*ann_inflation) -> 71643.138 | F8: =IF(des_rit_age>B7,C8-(D8+E8),0) -> 13765.896 | G8: =J7 -> 104562.51 | H8: =IF(des_rit_age>B7,G8*pre_inv_return,G8*post_inv_return) -> 8365.0004 | I8: =IF(des_rit_age>B7,0,E8) -> 0 | J8: =G8+(F8+H8)-I8 -> 126693.4 | K8: =J8-G8 -> 22130.896
A9: =1+A8 -> 8 | B9: =1+B8 -> 36 | C9: =IF(des_rit_age>B8,C8+(C8*ann_income_increase),0) -> 98694.883 | D9: =C9*tax_rate -> 9869.4883 | E9: =E8+(E8*ann_inflation) -> 73792.432 | F9: =IF(des_rit_age>B8,C9-(D9+E9),0) -> 15032.963 | G9: =J8 -> 126693.4 | H9: =IF(des_rit_age>B8,G9*pre_inv_return,G9*post_inv_return) -> 10135.472 | I9: =IF(des_rit_age>B8,0,E9) -> 0 | J9: =G9+(F9+H9)-I9 -> 151861.84 | K9: =J9-G9 -> 25168.435
A10: =1+A9 -> 9 | B10: =1+B9 -> 37 | C10: =IF(des_rit_age>B9,C9+(C9*ann_income_increase),0) -> 102642.68 | D10: =C10*tax_rate -> 10264.268 | E10: =E9+(E9*ann_inflation) -> 76006.205 | F10: =IF(des_rit_age>B9,C10-(D10+E10),0) -> 16372.206 | G10: =J9 -> 151861.84 | H10: =IF(des_rit_age>B9,G10*pre_inv_return,G10*post_inv_return) -> 12148.947 | I10: =IF(des_rit_age>B9,0,E10) -> 0 | J10: =G10+(F10+H10)-I10 -> 180382.99 | K10: =J10-G10 -> 28521.153
A11: =1+A10 -> 10 | B11: =1+B10 -> 38 | C11: =IF(des_rit_age>B10,C10+(C10*ann_income_increase),0) -> 106748.39 | D11: =C11*tax_rate -> 10674.839 | E11: =E10+(E10*ann_inflation) -> 78286.391 | F11: =IF(des_rit_age>B10,C11-(D11+E11),0) -> 17787.156 | G11: =J10 -> 180382.99 | H11: =IF(des_rit_age>B10,G11*pre_inv_return,G11*post_inv_return) -> 14430.639 | I11: =IF(des_rit_age>B10,0,E11) -> 0 | J11: =G11+(F11+H11)-I11 -> 212600.79 | K11: =J11-G11 -> 32217.796
A12: =1+A11 -> 11 | B12: =1+B11 -> 39 | C12: =IF(des_rit_age>B11,C11+(C11*ann_income_increase),0) -> 111018.32 | D12: =C12*tax_rate -> 11101.832 | E12: =E11+(E11*ann_inflation) -> 80634.983 | F12: =IF(des_rit_age>B11,C12-(D12+E12),0) -> 19281.506 | G12: =J11 -> 212600.79 | H12: =IF(des_rit_age>B11,G12*pre_inv_return,G12*post_inv_return) -> 17008.063 | I12: =IF(des_rit_age>B11,0,E12) -> 0 | J12: =G12+(F12+H12)-I12 -> 248890.35 | K12: =J12-G12 -> 36289.569
A13: =1+A12 -> 12 | B13: =1+B12 -> 40 | C13: =IF(des_rit_age>B12,C12+(C12*ann_income_increase),0) -> 115459.05 | D13: =C13*tax_rate -> 11545.905 | E13: =E12+(E12*ann_inflation) -> 83054.032 | F13: =IF(des_rit_age>B12,C13-(D13+E13),0) -> 20859.117 | G13: =J12 -> 248890.35 | H13: =IF(des_rit_age>B12,G13*pre_inv_return,G13*post_inv_return) -> 19911.228 | I13: =IF(des_rit_age>B12,0,E13) -> 0 | J13: =G13+(F13+H13)-I13 -> 289660.7 | K13: =J13-G13 -> 40770.345
A14: =1+A13 -> 13 | B14: =1+B13 -> 41 | C14: =IF(des_rit_age>B13,C13+(C13*ann_income_increase),0) -> 120077.42 | D14: =C14*tax_rate -> 12007.742 | E14: =E13+(E13*ann_inflation) -> 85545.653 | F14: =IF(des_rit_age>B13,C14-(D14+E14),0) -> 22524.022 | G14: =J13 -> 289660.7 | H14: =IF(des_rit_age>B13,G14*pre_inv_return,G14*post_inv_return) -> 23172.856 | I14: =IF(des_rit_age>B13,0,E14) -> 0 | J14: =G14+(F14+H14)-I14 -> 335357.58 | K14: =J14-G14 -> 45696.878
... A101: =1+A100 -> 100 | B101: =1+B100 -> 128 | C101: =IF(des_rit_age>B100,C100+(C100*ann_income_increase),0) -> 0 | D101: =C101*tax_rate -> 0 | E101: =E100+(E100*ann_inflation) -> 1119532 | F101: =IF(des_rit_age>B100,C101-(D101+E101),0) -> 0 | G101: =J100 -> -53659420 | H101: =IF(des_rit_age>B100,G101*pre_inv_return,G101*post_inv_return) -> -2146376.8 | I101: =IF(des_rit_age>B100,0,E101) -> 1119532 | J101: =G101+(F101+H101)-I101 -> -56925329 | K101: =J101-G101 -> -3265908.8

Sheet Support
A1: Conservative (Est. 4% Annual Return) | B1: 0.04
A2: Moderate (Est. 6% Annual Return) | B2: 0.06
A3: Aggressive (Est. 8% Annual Return) | B3: 0.08
A5: Pre-Retirement Investment Return | B5: =VLOOKUP(Planner!A16,Support!A1:B3,2,FALSE) -> 0.08
A6: Post-Retirement Investment Return | B6: =VLOOKUP(Planner!A19,Support!A1:B3,2,FALSE) -> 0.04
A8: Years Before Money Runs Out | B8: =COUNTIF(Calculations!J2:J101,">=0") -> 58
A9: Age When Money Runs Out | B9: =cur_age+years_before_money_runs_out -> 87
